encadre/__init__.py
encadre/controllers.py
encadre/framework.py
encadre_flask/__init__.py
encadre_flask/test.py
encadre_test_app/__init__.py
encadre_test_controllers/__init__.py
encadre-0.2.0.dist-info/METADATA
encadre-0.2.0.dist-info/WHEEL
encadre-0.2.0.dist-info/entry_points.txt
encadre-0.2.0.dist-info/top_level.txt
encadre-0.2.0.dist-info/RECORD
