Metadata-Version: 2.4
Name: encadre
Version: 0.2.0
Summary: Encadre framework
Author-email: Jean Schurger <jean@schurger.org>
License: GPLv3
Requires-Python: <3.12,>=3.10
Requires-Dist: Flask
Requires-Dist: fastjsonschema
Requires-Dist: flask-cors
Requires-Dist: decorator
Requires-Dist: flask_jwt_extended
Requires-Dist: cryptography
Provides-Extra: test
Requires-Dist: nose; extra == "test"
Requires-Dist: coverage; extra == "test"
